odoo/addons/partner_category_multi_company_account/README.rst
odoo/addons/partner_category_multi_company_account/__init__.py
odoo/addons/partner_category_multi_company_account/__manifest__.py
odoo/addons/partner_category_multi_company_account/i18n/it.po
odoo/addons/partner_category_multi_company_account/i18n/partner_category_multi_company_account.pot
odoo/addons/partner_category_multi_company_account/models/__init__.py
odoo/addons/partner_category_multi_company_account/models/account_reconcile_model.py
odoo/addons/partner_category_multi_company_account/readme/CONTRIBUTORS.rst
odoo/addons/partner_category_multi_company_account/readme/DESCRIPTION.rst
odoo/addons/partner_category_multi_company_account/static/description/icon.png
odoo/addons/partner_category_multi_company_account/static/description/index.html
odoo_addon_partner_category_multi_company_account-16.0.1.0.0.4.dist-info/METADATA
odoo_addon_partner_category_multi_company_account-16.0.1.0.0.4.dist-info/WHEEL
odoo_addon_partner_category_multi_company_account-16.0.1.0.0.4.dist-info/top_level.txt
odoo_addon_partner_category_multi_company_account-16.0.1.0.0.4.dist-info/RECORD
